pyghdet/__init__.py
pyghdet/pytorn.py
pyghdet-0.3.5.data/scripts/hdet_indiv.py
pyghdet-0.3.5.data/scripts/hdet_species.py
pyghdet-0.3.5.dist-info/LICENSE.rst
pyghdet-0.3.5.dist-info/METADATA
pyghdet-0.3.5.dist-info/WHEEL
pyghdet-0.3.5.dist-info/top_level.txt
pyghdet-0.3.5.dist-info/RECORD
