Metadata-Version: 2.1
Name: pyghdet
Version: 0.3.5
Summary: Global Hybridization detection using phylogenetic invariants
Home-page: https://github.com/rhaque62/pyghdet
Author: Rejuan Haque & Laura Kubatko
Author-email: haque.62@osu.edu
License: GPLv3
Classifier: Programming Language :: Python
Classifier: Programming Language :: Python :: 2
Classifier: Programming Language :: Python :: 2.7
Classifier: Programming Language :: Python :: 3
Classifier: Programming Language :: Python :: 3.6
Classifier: Programming Language :: Cython
Classifier: Development Status :: 3 - Alpha
Classifier: Intended Audience :: Science/Research
Classifier: License :: OSI Approved :: GNU General Public License v3 (GPLv3)
License-File: LICENSE.rst
